fluffy/__init__.py
fluffy/__main__.py
fluffy/config.py
fluffy/deliverables.py
fluffy/samplesheet.py
fluffy/singularity_cmd.py
fluffy/slurm_api.py
fluffy/status.py
fluffy/version.py
fluffy/cli/__init__.py
fluffy/cli/base.py
fluffy/cli/make_analysis.py
fluffy/cli/make_reference.py
fluffy/cli/make_rerun.py
fluffy/commands/__init__.py
fluffy/commands/amycne.py
fluffy/commands/bwa.py
fluffy/commands/multiqc.py
fluffy/commands/picard.py
fluffy/commands/pipelines.py
fluffy/commands/preface.py
fluffy/commands/tiddit.py
fluffy/commands/utils.py
fluffy/commands/wcx2cytosure.py
fluffy/commands/wisecondor.py
fluffy/scripts/filter_csv.py
fluffy/scripts/generate_csv.py
fluffy/scripts/merge_csv.py
fluffy/workflows/__init__.py
fluffy/workflows/align.py
fluffy/workflows/amycne.py
fluffy/workflows/analyse_samples.py
fluffy/workflows/cleanup.py
fluffy/workflows/picard.py
fluffy/workflows/preface.py
fluffy/workflows/status_update.py
fluffy/workflows/summarize.py
fluffy/workflows/wisecondor.py
cg_fluffy-4.0.0.dist-info/METADATA
cg_fluffy-4.0.0.dist-info/WHEEL
cg_fluffy-4.0.0.dist-info/entry_points.txt
cg_fluffy-4.0.0.dist-info/top_level.txt
cg_fluffy-4.0.0.dist-info/RECORD
