Metadata-Version: 2.1
Name: cg-fluffy
Version: 4.0.0
Summary: NIPT analysis pipeline
Home-page: https://github.com/Clinical-Genomics/fluffy
Author: Jesper Eisfeldt
Author-email: jesper.eisfeldt@scilifelab.com
License: MIT
Keywords: vcf,compression
Classifier: License :: OSI Approved :: MIT License
Classifier: Programming Language :: Python
Classifier: Programming Language :: Python :: 3
Classifier: Programming Language :: Python :: 3.6
Classifier: Operating System :: MacOS :: MacOS X
Classifier: Operating System :: Unix
Classifier: Intended Audience :: Science/Research
Requires-Python: >=3.6.0
Requires-Dist: click
Requires-Dist: coloredlogs
Requires-Dist: slurmpy
Requires-Dist: pyyaml
Requires-Dist: numpy
